{
  "_generic": {
    "defaultPackage": "@types/react-virtualized",
    "location": "",
    "packages": {
      "@types/react-virtualized": "9.21.21"
    },
    "sourcesAggregatedHash": null,
    "subsystem": "nodejs"
  },
  "_subsystem": {
    "nodejsVersion": "14"
  },
  "cyclicDependencies": {},
  "dependencies": {
    "@types/react": {
      "17.0.50": [
        [ "@types/prop-types", "15.7.5" ],
        [ "@types/scheduler", "0.16.2" ],
        [ "csstype", "3.1.1" ]
      ]
    },
    "@types/react-virtualized": {
      "9.21.21": [
        [ "@types/prop-types", "15.7.5" ],
        [ "@types/react", "17.0.50" ]
      ],
      "unknown": [
        [ "@types/react-virtualized", "9.21.21" ]
      ]
    }
  },
  "sources": {
    "@types/prop-types": {
      "15.7.5": {
        "hash": "sha512-JCB8C6SnDoQf0cNycqd/35A7MjcnK+ZTqE7judS6o7utxUCg6imJg3QK2qzHKszlTjcj2cn+NwMB2i96ubpj7w==",
        "type": "http",
        "url": "https://registry.npmjs.org/@types/prop-types/-/prop-types-15.7.5.tgz"
      }
    },
    "@types/react": {
      "17.0.50": {
        "hash": "sha512-ZCBHzpDb5skMnc1zFXAXnL3l1FAdi+xZvwxK+PkglMmBrwjpp9nKaWuEvrGnSifCJmBFGxZOOFuwC6KH/s0NuA==",
        "type": "http",
        "url": "https://registry.npmjs.org/@types/react/-/react-17.0.50.tgz"
      }
    },
    "@types/react-virtualized": {
      "9.21.21": {
        "hash": "sha512-Exx6I7p4Qn+BBA1SRyj/UwQlZ0I0Pq7g7uhAp0QQ4JWzZunqEqNBGTmCmMmS/3N9wFgAGWuBD16ap7k8Y14VPA==",
        "type": "http",
        "url": "https://registry.npmjs.org/@types/react-virtualized/-/react-virtualized-9.21.21.tgz"
      }
    },
    "@types/scheduler": {
      "0.16.2": {
        "hash": "sha512-hppQEBDmlwhFAXKJX2KnWLYu5yMfi91yazPb2l+lbJiwW+wdo1gNeRA+3RgNSO39WYX2euey41KEwnqesU2Jew==",
        "type": "http",
        "url": "https://registry.npmjs.org/@types/scheduler/-/scheduler-0.16.2.tgz"
      }
    },
    "csstype": {
      "3.1.1": {
        "hash": "sha512-DJR/VvkAvSZW9bTouZue2sSxDwdTN92uHjqeKVm+0dAqdfNykRzQ95tay8aXMBAAPpUiq4Qcug2L7neoRh2Egw==",
        "type": "http",
        "url": "https://registry.npmjs.org/csstype/-/csstype-3.1.1.tgz"
      }
    }
  }
}
