{
  "_generic": {
    "defaultPackage": "electron-to-chromium",
    "location": "",
    "packages": {
      "electron-to-chromium": "1.4.241"
    },
    "sourcesAggregatedHash": null,
    "subsystem": "nodejs"
  },
  "_subsystem": {
    "nodejsVersion": "14"
  },
  "cyclicDependencies": {},
  "dependencies": {
    "electron-to-chromium": {
      "unknown": [
        [ "electron-to-chromium", "1.4.241" ]
      ]
    }
  },
  "sources": {
    "electron-to-chromium": {
      "1.4.241": {
        "hash": "sha512-e7Wsh4ilaioBZ5bMm6+F4V5c11dh56/5Jwz7Hl5Tu1J7cnB+Pqx5qIF2iC7HPpfyQMqGSvvLP5bBAIDd2gAtGw==",
        "type": "http",
        "url": "https://registry.npmjs.org/electron-to-chromium/-/electron-to-chromium-1.4.241.tgz"
      }
    }
  }
}
