{
  "_generic": {
    "defaultPackage": "xterm",
    "location": "",
    "packages": {
      "xterm": "5.1.0-beta.35"
    },
    "sourcesAggregatedHash": null,
    "subsystem": "nodejs"
  },
  "_subsystem": {
    "nodejsVersion": "14"
  },
  "cyclicDependencies": {},
  "dependencies": {
    "xterm": {
      "unknown": [
        [ "xterm", "5.1.0-beta.35" ]
      ]
    }
  },
  "sources": {
    "xterm": {
      "5.1.0-beta.35": {
        "hash": "sha512-I5p7BwHObaAbkoOyJNwKNlmytEtAoQmR4xvYDBb5Ci4q4MM6bGtCvDnXKccOVRE787F0y4Ip6ZRJ0M1+Q+6z2w==",
        "type": "http",
        "url": "https://registry.npmjs.org/xterm/-/xterm-5.1.0-beta.35.tgz"
      }
    }
  }
}
