{
  "_generic": {
    "defaultPackage": "merge-stream",
    "location": "",
    "packages": {
      "merge-stream": "2.0.0"
    },
    "sourcesAggregatedHash": null,
    "subsystem": "nodejs"
  },
  "_subsystem": {
    "nodejsVersion": "14"
  },
  "cyclicDependencies": {},
  "dependencies": {
    "merge-stream": {
      "unknown": [
        [ "merge-stream", "2.0.0" ]
      ]
    }
  },
  "sources": {
    "merge-stream": {
      "2.0.0": {
        "hash": "sha512-abv/qOcuPfk3URPfDzmZU1LKmuw8kT+0nIHvKrKgFrwifol/doWcdA4ZqsWQ8ENrFKkd67Mfpo/LovbIUsbt3w==",
        "type": "http",
        "url": "https://registry.npmjs.org/merge-stream/-/merge-stream-2.0.0.tgz"
      }
    }
  }
}
