{
  "_generic": {
    "defaultPackage": "event-kit",
    "location": "",
    "packages": {
      "event-kit": "2.5.3"
    },
    "sourcesAggregatedHash": null,
    "subsystem": "nodejs"
  },
  "_subsystem": {
    "nodejsVersion": "14"
  },
  "cyclicDependencies": {},
  "dependencies": {
    "event-kit": {
      "unknown": [
        [ "event-kit", "2.5.3" ]
      ]
    }
  },
  "sources": {
    "event-kit": {
      "2.5.3": {
        "hash": "sha512-b7Qi1JNzY4BfAYfnIRanLk0DOD1gdkWHT4GISIn8Q2tAf3LpU8SP2CMwWaq40imYoKWbtN4ZhbSRxvsnikooZQ==",
        "type": "http",
        "url": "https://registry.npmjs.org/event-kit/-/event-kit-2.5.3.tgz"
      }
    }
  }
}
