{
  "_generic": {
    "defaultPackage": "xterm",
    "location": "",
    "packages": {
      "xterm": "5.1.0-beta.45"
    },
    "sourcesAggregatedHash": null,
    "subsystem": "nodejs"
  },
  "_subsystem": {
    "nodejsVersion": "14"
  },
  "cyclicDependencies": {},
  "dependencies": {
    "xterm": {
      "unknown": [
        [ "xterm", "5.1.0-beta.45" ]
      ]
    }
  },
  "sources": {
    "xterm": {
      "5.1.0-beta.45": {
        "hash": "sha512-M64EFaE7idNnPkQGWKoy/2x1gDWKOKUnOR1Yd7V4Abqx3B6d7NGhx/SnVC4Q0Fu4XpDC9kBVRxfBZahFPaH4Xg==",
        "type": "http",
        "url": "https://registry.npmjs.org/xterm/-/xterm-5.1.0-beta.45.tgz"
      }
    }
  }
}
