{
  "_generic": {
    "defaultPackage": "aws-cdk-lib",
    "location": "",
    "packages": {
      "aws-cdk-lib": "2.49.0"
    },
    "sourcesAggregatedHash": null,
    "subsystem": "nodejs"
  },
  "_subsystem": {
    "nodejsVersion": "14"
  },
  "cyclicDependencies": {},
  "dependencies": {
    "aws-cdk-lib": {
      "unknown": [
        [ "aws-cdk-lib", "2.49.0" ]
      ]
    }
  },
  "sources": {
    "aws-cdk-lib": {
      "2.49.0": {
        "hash": "sha512-HMrV41VaYVLFhm5i35bXuxiiib8IXPwuspDF7W3LJ4WVwxQZWx4eGcvRAdaXuNM7dDwM52cF5BNl8lYa/xCt5Q==",
        "type": "http",
        "url": "https://registry.npmjs.org/aws-cdk-lib/-/aws-cdk-lib-2.49.0.tgz"
      }
    },
    "constructs": {
      "10.1.144": {
        "hash": "sha512-mFHa7o+uG3Lag1oIjeh2N75ce8BDX5LYCOE67rm+P/b0dYiPS0iQz5PQgcWFdVFjTNJ3o4vvzw0rlui4j6i0+g==",
        "type": "http",
        "url": "https://registry.npmjs.org/constructs/-/constructs-10.1.144.tgz"
      }
    }
  }
}
