{
  "_generic": {
    "defaultPackage": "systeminformation",
    "location": "",
    "packages": {
      "systeminformation": "5.12.7"
    },
    "sourcesAggregatedHash": null,
    "subsystem": "nodejs"
  },
  "_subsystem": {
    "nodejsVersion": "14"
  },
  "cyclicDependencies": {},
  "dependencies": {
    "systeminformation": {
      "unknown": [
        [ "systeminformation", "5.12.7" ]
      ]
    }
  },
  "sources": {
    "systeminformation": {
      "5.12.7": {
        "hash": "sha512-Kubdu6YzMWtGEsnGF5ddohvIWsxOlEkV0P/3oKTPl56ADOowDiWBR59RpIRvbijXwEQrnRKeF3MOuH7apdEc/g==",
        "type": "http",
        "url": "https://registry.npmjs.org/systeminformation/-/systeminformation-5.12.7.tgz"
      }
    }
  }
}
