{
  "_generic": {
    "defaultPackage": "console-polyfill",
    "location": "",
    "packages": {
      "console-polyfill": "0.3.0"
    },
    "sourcesAggregatedHash": null,
    "subsystem": "nodejs"
  },
  "_subsystem": {
    "nodejsVersion": "14"
  },
  "cyclicDependencies": {},
  "dependencies": {
    "console-polyfill": {
      "unknown": [
        [ "console-polyfill", "0.3.0" ]
      ]
    }
  },
  "sources": {
    "console-polyfill": {
      "0.3.0": {
        "hash": "sha512-w+JSDZS7XML43Xnwo2x5O5vxB0ID7T5BdqDtyqT6uiCAX2kZAgcWxNaGqT97tZfSHzfOcvrfsDAodKcJ3UvnXQ==",
        "type": "http",
        "url": "https://registry.npmjs.org/console-polyfill/-/console-polyfill-0.3.0.tgz"
      }
    }
  }
}
